generate_waveform/__init__.py
generate_waveform/server.py
tests/__init__.py
tests/test_generate_waveform.py
generate_waveform-0.1.4.dist-info/METADATA
generate_waveform-0.1.4.dist-info/WHEEL
generate_waveform-0.1.4.dist-info/top_level.txt
generate_waveform-0.1.4.dist-info/RECORD
